{"images": [{"file_name": "2009_000503.jpg", "height": 375, "width": 500, "id": 2009000503}, {"file_name": "2008_002647.jpg", "height": 400, "width": 500, "id": 2008002647}, {"file_name": "2009_001044.jpg", "height": 375, "width": 500, "id": 2009001044}, {"file_name": "2008_007797.jpg", "height": 500, "width": 375, "id": 2008007797}, {"file_name": "004571.jpg", "height": 323, "width": 500, "id": 4571}, {"file_name": "2008_005243.jpg", "height": 335, "width": 500, "id": 2008005243}, {"file_name": "006585.jpg", "height": 331, "width": 500, "id": 6585}, {"file_name": "2010_002531.jpg", "height": 375, "width": 500, "id": 2010002531}, {"file_name": "002047.jpg", "height": 375, "width": 500, "id": 2047}, {"file_name": "2009_002765.jpg", "height": 333, "width": 500, "id": 2009002765}, {"file_name": "2009_002272.jpg", "height": 334, "width": 500, "id": 2009002272}, {"file_name": "2008_007357.jpg", "height": 334, "width": 500, "id": 2008007357}, {"file_name": "2010_000477.jpg", "height": 234, "width": 500, "id": 2010000477}, {"file_name": "004983.jpg", "height": 500, "width": 338, "id": 4983}, {"file_name": "001455.jpg", "height": 374, "width": 500, "id": 1455}, {"file_name": "2009_004876.jpg", "height": 500, "width": 375, "id": 2009004876}, {"file_name": "2009_002058.jpg", "height": 500, "width": 375, "id": 2009002058}, {"file_name": "2008_003652.jpg", "height": 375, "width": 500, "id": 2008003652}, {"file_name": "2008_001823.jpg", "height": 71, "width": 500, "id": 2008001823}, {"file_name": "2009_000996.jpg", "height": 375, "width": 500, "id": 2009000996}, {"file_name": "2010_004866.jpg", "height": 333, "width": 500, "id": 2010004866}, {"file_name": "000498.jpg", "height": 500, "width": 326, "id": 498}, {"file_name": "001346.jpg", "height": 229, "width": 500, "id": 1346}, {"file_name": "2009_002579.jpg", "height": 500, "width": 375, "id": 2009002579}, {"file_name": "2011_001033.jpg", "height": 375, "width": 500, "id": 2011001033}, {"file_name": "2008_007662.jpg", "height": 355, "width": 500, "id": 2008007662}, {"file_name": "2010_000009.jpg", "height": 333, "width": 500, "id": 2010000009}, {"file_name": "2010_002973.jpg", "height": 500, "width": 388, "id": 2010002973}, {"file_name": "2010_003677.jpg", "height": 500, "width": 375, "id": 2010003677}, {"file_name": "2008_005107.jpg", "height": 500, "width": 375, "id": 2008005107}, {"file_name": "2010_000669.jpg", "height": 375, "width": 500, "id": 2010000669}, {"file_name": "2011_003183.jpg", "height": 375, "width": 500, "id": 2011003183}, {"file_name": "2011_003166.jpg", "height": 375, "width": 500, "id": 2011003166}, {"file_name": "2008_007875.jpg", "height": 375, "width": 500, "id": 2008007875}, {"file_name": "2008_003975.jpg", "height": 333, "width": 500, "id": 2008003975}, {"file_name": "2009_001006.jpg", "height": 333, "width": 500, "id": 2009001006}, {"file_name": "2011_000449.jpg", "height": 329, "width": 500, "id": 2011000449}, {"file_name": "2009_003294.jpg", "height": 333, "width": 500, "id": 2009003294}, {"file_name": "2009_002165.jpg", "height": 375, "width": 500, "id": 2009002165}, {"file_name": "004487.jpg", "height": 500, "width": 334, "id": 4487}, {"file_name": "2008_007108.jpg", "height": 363, "width": 500, "id": 2008007108}, {"file_name": "002330.jpg", "height": 357, "width": 500, "id": 2330}, {"file_name": "2010_003094.jpg", "height": 500, "width": 377, "id": 2010003094}, {"file_name": "2008_005763.jpg", "height": 311, "width": 500, "id": 2008005763}, {"file_name": "2011_002379.jpg", "height": 375, "width": 500, "id": 2011002379}, {"file_name": "2011_003228.jpg", "height": 375, "width": 500, "id": 2011003228}, {"file_name": "2009_001468.jpg", "height": 500, "width": 375, "id": 2009001468}, {"file_name": "2008_003434.jpg", "height": 375, "width": 500, "id": 2008003434}, {"file_name": "2010_005190.jpg", "height": 500, "width": 375, "id": 2010005190}, {"file_name": "2011_002532.jpg", "height": 375, "width": 500, "id": 2011002532}], "annotations": [{"segmentation": [[125, 111, 125, 265, 235, 265, 235, 111]], "area": 16940, "iscrowd": 0, "image_id": 2009000503, "bbox": [125, 111, 110, 154], "category_id": 3, "id": 22308, "ignore": 0}, {"segmentation": [[101, 71, 101, 272, 252, 272, 252, 71]], "area": 30351, "iscrowd": 0, "image_id": 2008002647, "bbox": [101, 71, 151, 201], "category_id": 3, "id": 17509, "ignore": 0}, {"segmentation": [[74, 106, 74, 295, 463, 295, 463, 106]], "area": 73521, "iscrowd": 0, "image_id": 2009001044, "bbox": [74, 106, 389, 189], "category_id": 6, "id": 38449, "ignore": 0}, {"segmentation": [[57, 107, 57, 413, 375, 413, 375, 107]], "area": 97308, "iscrowd": 0, "image_id": 2008007797, "bbox": [57, 107, 318, 306], "category_id": 6, "id": 37053, "ignore": 0}, {"segmentation": [[223, 119, 223, 243, 387, 243, 387, 119]], "area": 20336, "iscrowd": 0, "image_id": 4571, "bbox": [223, 119, 164, 124], "category_id": 10, "id": 3507, "ignore": 0}, {"segmentation": [[55, 41, 55, 236, 168, 236, 168, 41]], "area": 22035, "iscrowd": 0, "image_id": 4571, "bbox": [55, 41, 113, 195], "category_id": 10, "id": 3508, "ignore": 0}, {"segmentation": [[208, 50, 208, 157, 239, 157, 239, 50]], "area": 3317, "iscrowd": 0, "image_id": 4571, "bbox": [208, 50, 31, 107], "category_id": 15, "id": 3509, "ignore": 0}, {"segmentation": [[236, 55, 236, 150, 263, 150, 263, 55]], "area": 2565, "iscrowd": 0, "image_id": 4571, "bbox": [236, 55, 27, 95], "category_id": 15, "id": 3510, "ignore": 0}, {"segmentation": [[236, 148, 236, 241, 327, 241, 327, 148]], "area": 8463, "iscrowd": 0, "image_id": 2008005243, "bbox": [236, 148, 91, 93], "category_id": 14, "id": 35220, "ignore": 0}, {"segmentation": [[226, 111, 226, 197, 326, 197, 326, 111]], "area": 8600, "iscrowd": 0, "image_id": 2008005243, "bbox": [226, 111, 100, 86], "category_id": 15, "id": 35221, "ignore": 0}, {"segmentation": [[167, 40, 167, 234, 325, 234, 325, 40]], "area": 30652, "iscrowd": 0, "image_id": 6585, "bbox": [167, 40, 158, 194], "category_id": 15, "id": 13038, "ignore": 0}, {"segmentation": [[142, 100, 142, 258, 331, 258, 331, 100]], "area": 29862, "iscrowd": 0, "image_id": 6585, "bbox": [142, 100, 189, 158], "category_id": 14, "id": 13039, "ignore": 0}, {"segmentation": [[105, 33, 105, 237, 494, 237, 494, 33]], "area": 79356, "iscrowd": 0, "image_id": 2010002531, "bbox": [105, 33, 389, 204], "category_id": 8, "id": 42705, "ignore": 0}, {"segmentation": [[0, 0, 0, 375, 500, 375, 500, 0]], "area": 187500, "iscrowd": 0, "image_id": 2010002531, "bbox": [0, 0, 500, 375], "category_id": 18, "id": 42706, "ignore": 0}, {"segmentation": [[209, 224, 209, 285, 295, 285, 295, 224]], "area": 5246, "iscrowd": 0, "image_id": 2047, "bbox": [209, 224, 86, 61], "category_id": 18, "id": 1550, "ignore": 0}, {"segmentation": [[124, 111, 124, 197, 211, 197, 211, 111]], "area": 7482, "iscrowd": 0, "image_id": 2009002765, "bbox": [124, 111, 87, 86], "category_id": 1, "id": 39545, "ignore": 0}, {"segmentation": [[51, 67, 51, 223, 431, 223, 431, 67]], "area": 59280, "iscrowd": 0, "image_id": 2009002272, "bbox": [51, 67, 380, 156], "category_id": 1, "id": 39166, "ignore": 0}, {"segmentation": [[211, 116, 211, 155, 341, 155, 341, 116]], "area": 5070, "iscrowd": 0, "image_id": 2008007357, "bbox": [211, 116, 130, 39], "category_id": 1, "id": 20910, "ignore": 0}, {"segmentation": [[10, 17, 10, 228, 488, 228, 488, 17]], "area": 100858, "iscrowd": 0, "image_id": 2010000477, "bbox": [10, 17, 478, 211], "category_id": 1, "id": 25664, "ignore": 0}, {"segmentation": [[78, 49, 78, 440, 265, 440, 265, 49]], "area": 73117, "iscrowd": 0, "image_id": 4983, "bbox": [78, 49, 187, 391], "category_id": 2, "id": 11752, "ignore": 0}, {"segmentation": [[0, 0, 0, 82, 317, 82, 317, 0]], "area": 25994, "iscrowd": 0, "image_id": 4983, "bbox": [0, 0, 317, 82], "category_id": 7, "id": 11753, "ignore": 0}, {"segmentation": [[124, 175, 124, 374, 345, 374, 345, 175]], "area": 43979, "iscrowd": 0, "image_id": 1455, "bbox": [124, 175, 221, 199], "category_id": 2, "id": 1086, "ignore": 0}, {"segmentation": [[146, 123, 146, 345, 300, 345, 300, 123]], "area": 34188, "iscrowd": 0, "image_id": 1455, "bbox": [146, 123, 154, 222], "category_id": 15, "id": 1087, "ignore": 0}, {"segmentation": [[50, 124, 50, 187, 92, 187, 92, 124]], "area": 2646, "iscrowd": 0, "image_id": 1455, "bbox": [50, 124, 42, 63], "category_id": 15, "id": 1088, "ignore": 0}, {"segmentation": [[99, 121, 99, 182, 153, 182, 153, 121]], "area": 3294, "iscrowd": 0, "image_id": 1455, "bbox": [99, 121, 54, 61], "category_id": 15, "id": 1089, "ignore": 0}, {"segmentation": [[414, 88, 414, 126, 500, 126, 500, 88]], "area": 3268, "iscrowd": 0, "image_id": 1455, "bbox": [414, 88, 86, 38], "category_id": 7, "id": 1090, "ignore": 0}, {"segmentation": [[0, 0, 0, 481, 375, 481, 375, 0]], "area": 180375, "iscrowd": 0, "image_id": 2009004876, "bbox": [0, 0, 375, 481], "category_id": 2, "id": 40949, "ignore": 0}, {"segmentation": [[80, 389, 80, 500, 375, 500, 375, 389]], "area": 32745, "iscrowd": 0, "image_id": 2009002058, "bbox": [80, 389, 295, 111], "category_id": 2, "id": 39036, "ignore": 0}, {"segmentation": [[223, 102, 223, 500, 375, 500, 375, 102]], "area": 60496, "iscrowd": 0, "image_id": 2009002058, "bbox": [223, 102, 152, 398], "category_id": 15, "id": 39037, "ignore": 0}, {"segmentation": [[0, 180, 0, 484, 142, 484, 142, 180]], "area": 43168, "iscrowd": 0, "image_id": 2009002058, "bbox": [0, 180, 142, 304], "category_id": 7, "id": 39038, "ignore": 0}, {"segmentation": [[232, 277, 232, 324, 343, 324, 343, 277]], "area": 5217, "iscrowd": 0, "image_id": 2008003652, "bbox": [232, 277, 111, 47], "category_id": 4, "id": 18196, "ignore": 0}, {"segmentation": [[36, 43, 36, 70, 103, 70, 103, 43]], "area": 1809, "iscrowd": 0, "image_id": 2008001823, "bbox": [36, 43, 67, 27], "category_id": 4, "id": 32695, "ignore": 0}, {"segmentation": [[123, 92, 123, 243, 245, 243, 245, 92]], "area": 18422, "iscrowd": 0, "image_id": 2009000996, "bbox": [123, 92, 122, 151], "category_id": 4, "id": 22604, "ignore": 0}, {"segmentation": [[234, 189, 234, 245, 451, 245, 451, 189]], "area": 12152, "iscrowd": 0, "image_id": 2009000996, "bbox": [234, 189, 217, 56], "category_id": 4, "id": 22605, "ignore": 0}, {"segmentation": [[168, 95, 168, 295, 228, 295, 228, 95]], "area": 12000, "iscrowd": 0, "image_id": 2010004866, "bbox": [168, 95, 60, 200], "category_id": 5, "id": 44082, "ignore": 0}, {"segmentation": [[5, 4, 5, 203, 176, 203, 176, 4]], "area": 34029, "iscrowd": 0, "image_id": 498, "bbox": [5, 4, 171, 199], "category_id": 5, "id": 8210, "ignore": 0}, {"segmentation": [[113, 255, 113, 496, 201, 496, 201, 255]], "area": 21208, "iscrowd": 0, "image_id": 498, "bbox": [113, 255, 88, 241], "category_id": 15, "id": 8211, "ignore": 0}, {"segmentation": [[308, 96, 308, 229, 356, 229, 356, 96]], "area": 6384, "iscrowd": 0, "image_id": 1346, "bbox": [308, 96, 48, 133], "category_id": 5, "id": 994, "ignore": 0}, {"segmentation": [[219, 3, 219, 229, 447, 229, 447, 3]], "area": 51528, "iscrowd": 0, "image_id": 1346, "bbox": [219, 3, 228, 226], "category_id": 15, "id": 995, "ignore": 0}, {"segmentation": [[6, 0, 6, 228, 262, 228, 262, 0]], "area": 58368, "iscrowd": 0, "image_id": 1346, "bbox": [6, 0, 256, 228], "category_id": 15, "id": 996, "ignore": 0}, {"segmentation": [[111, 150, 111, 376, 270, 376, 270, 150]], "area": 35934, "iscrowd": 0, "image_id": 2009002579, "bbox": [111, 150, 159, 226], "category_id": 15, "id": 23645, "ignore": 0}, {"segmentation": [[0, 315, 0, 500, 375, 500, 375, 315]], "area": 69375, "iscrowd": 0, "image_id": 2009002579, "bbox": [0, 315, 375, 185], "category_id": 11, "id": 23646, "ignore": 0}, {"segmentation": [[34, 195, 34, 500, 119, 500, 119, 195]], "area": 25925, "iscrowd": 0, "image_id": 2009002579, "bbox": [34, 195, 85, 305], "category_id": 5, "id": 23647, "ignore": 0}, {"segmentation": [[130, 204, 130, 472, 199, 472, 199, 204]], "area": 18492, "iscrowd": 0, "image_id": 2009002579, "bbox": [130, 204, 69, 268], "category_id": 5, "id": 23648, "ignore": 0}, {"segmentation": [[194, 278, 194, 423, 240, 423, 240, 278]], "area": 6670, "iscrowd": 0, "image_id": 2009002579, "bbox": [194, 278, 46, 145], "category_id": 5, "id": 23649, "ignore": 0}, {"segmentation": [[75, 193, 75, 256, 165, 256, 165, 193]], "area": 5670, "iscrowd": 0, "image_id": 2011001033, "bbox": [75, 193, 90, 63], "category_id": 7, "id": 29813, "ignore": 0}, {"segmentation": [[191, 77, 191, 297, 334, 297, 334, 77]], "area": 31460, "iscrowd": 0, "image_id": 2008007662, "bbox": [191, 77, 143, 220], "category_id": 8, "id": 36959, "ignore": 0}, {"segmentation": [[159, 29, 159, 312, 345, 312, 345, 29]], "area": 52638, "iscrowd": 0, "image_id": 2010000009, "bbox": [159, 29, 186, 283], "category_id": 8, "id": 25424, "ignore": 0}, {"segmentation": [[18, 7, 18, 452, 359, 452, 359, 7]], "area": 151745, "iscrowd": 0, "image_id": 2010002973, "bbox": [18, 7, 341, 445], "category_id": 8, "id": 27133, "ignore": 0}, {"segmentation": [[0, 0, 0, 500, 375, 500, 375, 0]], "area": 187500, "iscrowd": 0, "image_id": 2010003677, "bbox": [0, 0, 375, 500], "category_id": 9, "id": 27547, "ignore": 0}, {"segmentation": [[37, 93, 37, 500, 271, 500, 271, 93]], "area": 95238, "iscrowd": 0, "image_id": 2010003677, "bbox": [37, 93, 234, 407], "category_id": 15, "id": 27548, "ignore": 0}, {"segmentation": [[95, 160, 95, 500, 375, 500, 375, 160]], "area": 95200, "iscrowd": 0, "image_id": 2008005107, "bbox": [95, 160, 280, 340], "category_id": 15, "id": 35100, "ignore": 0}, {"segmentation": [[0, 74, 0, 500, 375, 500, 375, 74]], "area": 159750, "iscrowd": 0, "image_id": 2008005107, "bbox": [0, 74, 375, 426], "category_id": 9, "id": 35101, "ignore": 0}, {"segmentation": [[0, 300, 0, 373, 230, 373, 230, 300]], "area": 16790, "iscrowd": 0, "image_id": 2010000669, "bbox": [0, 300, 230, 73], "category_id": 11, "id": 41594, "ignore": 0}, {"segmentation": [[52, 266, 52, 316, 122, 316, 122, 266]], "area": 3500, "iscrowd": 0, "image_id": 2010000669, "bbox": [52, 266, 70, 50], "category_id": 9, "id": 41595, "ignore": 0}, {"segmentation": [[0, 313, 0, 374, 111, 374, 111, 313]], "area": 6771, "iscrowd": 0, "image_id": 2010000669, "bbox": [0, 313, 111, 61], "category_id": 9, "id": 41596, "ignore": 0}, {"segmentation": [[199, 123, 199, 176, 271, 176, 271, 123]], "area": 3816, "iscrowd": 0, "image_id": 2010000669, "bbox": [199, 123, 72, 53], "category_id": 20, "id": 41597, "ignore": 0}, {"segmentation": [[308, 72, 308, 178, 384, 178, 384, 72]], "area": 8056, "iscrowd": 0, "image_id": 2010000669, "bbox": [308, 72, 76, 106], "category_id": 16, "id": 41598, "ignore": 0}, {"segmentation": [[175, 196, 175, 330, 374, 330, 374, 196]], "area": 26666, "iscrowd": 0, "image_id": 2011003183, "bbox": [175, 196, 199, 134], "category_id": 11, "id": 31392, "ignore": 0}, {"segmentation": [[168, 202, 168, 329, 248, 329, 248, 202]], "area": 10160, "iscrowd": 0, "image_id": 2011003183, "bbox": [168, 202, 80, 127], "category_id": 9, "id": 31393, "ignore": 0}, {"segmentation": [[259, 207, 259, 328, 332, 328, 332, 207]], "area": 8833, "iscrowd": 0, "image_id": 2011003183, "bbox": [259, 207, 73, 121], "category_id": 9, "id": 31394, "ignore": 0}, {"segmentation": [[217, 187, 217, 301, 283, 301, 283, 187]], "area": 7524, "iscrowd": 0, "image_id": 2011003183, "bbox": [217, 187, 66, 114], "category_id": 9, "id": 31395, "ignore": 0}, {"segmentation": [[285, 190, 285, 301, 349, 301, 349, 190]], "area": 7104, "iscrowd": 0, "image_id": 2011003183, "bbox": [285, 190, 64, 111], "category_id": 9, "id": 31396, "ignore": 0}, {"segmentation": [[2, 108, 2, 375, 498, 375, 498, 108]], "area": 132432, "iscrowd": 0, "image_id": 2011003166, "bbox": [2, 108, 496, 267], "category_id": 11, "id": 47124, "ignore": 0}, {"segmentation": [[189, 52, 189, 114, 214, 114, 214, 52]], "area": 1550, "iscrowd": 0, "image_id": 2011003166, "bbox": [189, 52, 25, 62], "category_id": 5, "id": 47125, "ignore": 0}, {"segmentation": [[137, 144, 137, 334, 388, 334, 388, 144]], "area": 47690, "iscrowd": 0, "image_id": 2011003166, "bbox": [137, 144, 251, 190], "category_id": 8, "id": 47126, "ignore": 0}, {"segmentation": [[316, 0, 316, 162, 500, 162, 500, 0]], "area": 29808, "iscrowd": 0, "image_id": 2011003166, "bbox": [316, 0, 184, 162], "category_id": 9, "id": 47127, "ignore": 0}, {"segmentation": [[185, 38, 185, 317, 310, 317, 310, 38]], "area": 34875, "iscrowd": 0, "image_id": 2008007875, "bbox": [185, 38, 125, 279], "category_id": 12, "id": 37125, "ignore": 0}, {"segmentation": [[0, 0, 0, 332, 500, 332, 500, 0]], "area": 166000, "iscrowd": 0, "image_id": 2008003975, "bbox": [0, 0, 500, 332], "category_id": 12, "id": 18453, "ignore": 0}, {"segmentation": [[64, 0, 64, 223, 256, 223, 256, 0]], "area": 42816, "iscrowd": 0, "image_id": 2009001006, "bbox": [64, 0, 192, 223], "category_id": 12, "id": 38414, "ignore": 0}, {"segmentation": [[103, 9, 103, 314, 427, 314, 427, 9]], "area": 98820, "iscrowd": 0, "image_id": 2011000449, "bbox": [103, 9, 324, 305], "category_id": 12, "id": 29277, "ignore": 0}, {"segmentation": [[206, 37, 206, 310, 393, 310, 393, 37]], "area": 51051, "iscrowd": 0, "image_id": 2009003294, "bbox": [206, 37, 187, 273], "category_id": 13, "id": 39906, "ignore": 0}, {"segmentation": [[212, 26, 212, 182, 313, 182, 313, 26]], "area": 15756, "iscrowd": 0, "image_id": 2009003294, "bbox": [212, 26, 101, 156], "category_id": 15, "id": 39907, "ignore": 0}, {"segmentation": [[142, 109, 142, 251, 377, 251, 377, 109]], "area": 33370, "iscrowd": 0, "image_id": 2009002165, "bbox": [142, 109, 235, 142], "category_id": 13, "id": 39096, "ignore": 0}, {"segmentation": [[108, 133, 108, 293, 339, 293, 339, 133]], "area": 36960, "iscrowd": 0, "image_id": 2009002165, "bbox": [108, 133, 231, 160], "category_id": 13, "id": 39097, "ignore": 0}, {"segmentation": [[62, 156, 62, 418, 227, 418, 227, 156]], "area": 43230, "iscrowd": 0, "image_id": 4487, "bbox": [62, 156, 165, 262], "category_id": 13, "id": 11395, "ignore": 0}, {"segmentation": [[59, 40, 59, 252, 196, 252, 196, 40]], "area": 29044, "iscrowd": 0, "image_id": 4487, "bbox": [59, 40, 137, 212], "category_id": 15, "id": 11396, "ignore": 0}, {"segmentation": [[25, 134, 25, 236, 106, 236, 106, 134]], "area": 8262, "iscrowd": 0, "image_id": 2008007108, "bbox": [25, 134, 81, 102], "category_id": 16, "id": 36533, "ignore": 0}, {"segmentation": [[167, 70, 167, 154, 234, 154, 234, 70]], "area": 5628, "iscrowd": 0, "image_id": 2008007108, "bbox": [167, 70, 67, 84], "category_id": 16, "id": 36534, "ignore": 0}, {"segmentation": [[240, 70, 240, 127, 315, 127, 315, 70]], "area": 4275, "iscrowd": 0, "image_id": 2008007108, "bbox": [240, 70, 75, 57], "category_id": 16, "id": 36535, "ignore": 0}, {"segmentation": [[265, 27, 265, 68, 300, 68, 300, 27]], "area": 1435, "iscrowd": 0, "image_id": 2008007108, "bbox": [265, 27, 35, 41], "category_id": 16, "id": 36536, "ignore": 0}, {"segmentation": [[288, 93, 288, 171, 355, 171, 355, 93]], "area": 5226, "iscrowd": 0, "image_id": 2008007108, "bbox": [288, 93, 67, 78], "category_id": 16, "id": 36537, "ignore": 0}, {"segmentation": [[337, 114, 337, 201, 412, 201, 412, 114]], "area": 6525, "iscrowd": 0, "image_id": 2008007108, "bbox": [337, 114, 75, 87], "category_id": 16, "id": 36538, "ignore": 0}, {"segmentation": [[400, 154, 400, 233, 455, 233, 455, 154]], "area": 4345, "iscrowd": 0, "image_id": 2008007108, "bbox": [400, 154, 55, 79], "category_id": 16, "id": 36539, "ignore": 0}, {"segmentation": [[211, 213, 211, 332, 351, 332, 351, 213]], "area": 16660, "iscrowd": 0, "image_id": 2008007108, "bbox": [211, 213, 140, 119], "category_id": 12, "id": 36540, "ignore": 0}, {"segmentation": [[235, 1, 235, 61, 261, 61, 261, 1]], "area": 1560, "iscrowd": 0, "image_id": 2008007108, "bbox": [235, 1, 26, 60], "category_id": 16, "id": 36541, "ignore": 0}, {"segmentation": [[304, 153, 304, 221, 395, 221, 395, 153]], "area": 6188, "iscrowd": 0, "image_id": 2330, "bbox": [304, 153, 91, 68], "category_id": 17, "id": 9676, "ignore": 0}, {"segmentation": [[32, 119, 32, 180, 164, 180, 164, 119]], "area": 8052, "iscrowd": 0, "image_id": 2330, "bbox": [32, 119, 132, 61], "category_id": 17, "id": 9677, "ignore": 0}, {"segmentation": [[303, 251, 303, 403, 370, 403, 370, 251]], "area": 10184, "iscrowd": 0, "image_id": 2010003094, "bbox": [303, 251, 67, 152], "category_id": 17, "id": 27230, "ignore": 0}, {"segmentation": [[0, 330, 0, 460, 124, 460, 124, 330]], "area": 16120, "iscrowd": 0, "image_id": 2010003094, "bbox": [0, 330, 124, 130], "category_id": 17, "id": 27231, "ignore": 0}, {"segmentation": [[80, 127, 80, 481, 346, 481, 346, 127]], "area": 94164, "iscrowd": 0, "image_id": 2010003094, "bbox": [80, 127, 266, 354], "category_id": 15, "id": 27232, "ignore": 0}, {"segmentation": [[39, 82, 39, 245, 399, 245, 399, 82]], "area": 58680, "iscrowd": 0, "image_id": 2008005763, "bbox": [39, 82, 360, 163], "category_id": 19, "id": 35573, "ignore": 0}, {"segmentation": [[141, 107, 141, 261, 293, 261, 293, 107]], "area": 23408, "iscrowd": 0, "image_id": 2011002379, "bbox": [141, 107, 152, 154], "category_id": 19, "id": 46522, "ignore": 0}, {"segmentation": [[0, 0, 0, 345, 500, 345, 500, 0]], "area": 172500, "iscrowd": 0, "image_id": 2011003228, "bbox": [0, 0, 500, 345], "category_id": 19, "id": 47169, "ignore": 0}, {"segmentation": [[47, 150, 47, 334, 247, 334, 247, 150]], "area": 36800, "iscrowd": 0, "image_id": 2009001468, "bbox": [47, 150, 200, 184], "category_id": 19, "id": 38695, "ignore": 0}, {"segmentation": [[276, 255, 276, 437, 335, 437, 335, 255]], "area": 10738, "iscrowd": 0, "image_id": 2009001468, "bbox": [276, 255, 59, 182], "category_id": 15, "id": 38696, "ignore": 0}, {"segmentation": [[215, 67, 215, 231, 458, 231, 458, 67]], "area": 39852, "iscrowd": 0, "image_id": 2008003434, "bbox": [215, 67, 243, 164], "category_id": 20, "id": 18043, "ignore": 0}, {"segmentation": [[59, 263, 59, 322, 120, 322, 120, 263]], "area": 3599, "iscrowd": 0, "image_id": 2008003434, "bbox": [59, 263, 61, 59], "category_id": 16, "id": 18044, "ignore": 0}, {"segmentation": [[16, 125, 16, 296, 98, 296, 98, 125]], "area": 14022, "iscrowd": 0, "image_id": 2008003434, "bbox": [16, 125, 82, 171], "category_id": 16, "id": 18045, "ignore": 0}, {"segmentation": [[30, 185, 30, 326, 165, 326, 165, 185]], "area": 19035, "iscrowd": 0, "image_id": 2010005190, "bbox": [30, 185, 135, 141], "category_id": 20, "id": 28437, "ignore": 0}, {"segmentation": [[250, 40, 250, 176, 426, 176, 426, 40]], "area": 23936, "iscrowd": 0, "image_id": 2011002532, "bbox": [250, 40, 176, 136], "category_id": 20, "id": 46607, "ignore": 0}, {"segmentation": [[16, 40, 16, 181, 193, 181, 193, 40]], "area": 24957, "iscrowd": 0, "image_id": 2011002532, "bbox": [16, 40, 177, 141], "category_id": 20, "id": 46608, "ignore": 0}, {"segmentation": [[0, 174, 0, 291, 33, 291, 33, 174]], "area": 3861, "iscrowd": 0, "image_id": 2011002532, "bbox": [0, 174, 33, 117], "category_id": 15, "id": 46609, "ignore": 0}, {"segmentation": [[288, 182, 288, 267, 372, 267, 372, 182]], "area": 7140, "iscrowd": 0, "image_id": 2011002532, "bbox": [288, 182, 84, 85], "category_id": 15, "id": 46610, "ignore": 0}], "categories": [{"supercategory": "none", "id": 1, "name": "aeroplane"}, {"supercategory": "none", "id": 2, "name": "bicycle"}, {"supercategory": "none", "id": 3, "name": "bird"}, {"supercategory": "none", "id": 4, "name": "boat"}, {"supercategory": "none", "id": 5, "name": "bottle"}, {"supercategory": "none", "id": 6, "name": "bus"}, {"supercategory": "none", "id": 7, "name": "car"}, {"supercategory": "none", "id": 8, "name": "cat"}, {"supercategory": "none", "id": 9, "name": "chair"}, {"supercategory": "none", "id": 10, "name": "cow"}, {"supercategory": "none", "id": 11, "name": "diningtable"}, {"supercategory": "none", "id": 12, "name": "dog"}, {"supercategory": "none", "id": 13, "name": "horse"}, {"supercategory": "none", "id": 14, "name": "motorbike"}, {"supercategory": "none", "id": 15, "name": "person"}, {"supercategory": "none", "id": 16, "name": "pottedplant"}, {"supercategory": "none", "id": 17, "name": "sheep"}, {"supercategory": "none", "id": 18, "name": "sofa"}, {"supercategory": "none", "id": 19, "name": "train"}, {"supercategory": "none", "id": 20, "name": "tvmonitor"}]}